{"update_at":"2021-03-15T06:42:06.432Z","today":[{"url":"https://api.github.com/repos/jwenjian/reading-list/issues/103","repository_url":"https://api.github.com/repos/jwenjian/reading-list","labels_url":"https://api.github.com/repos/jwenjian/reading-list/issues/103/labels{/name}","comments_url":"https://api.github.com/repos/jwenjian/reading-list/issues/103/comments","events_url":"https://api.github.com/repos/jwenjian/reading-list/issues/103/events","html_url":"https://github.com/jwenjian/reading-list/issues/103","id":831476412,"node_id":"MDU6SXNzdWU4MzE0NzY0MTI=","number":103,"title":"由于所有主流浏览器都已经移除了 NPAPI 的支持，Oracle 将 Applet API 标记为 “即将移除（for removal）” ","user":{"login":"jwenjian","id":25657798,"node_id":"MDQ6VXNlcjI1NjU3Nzk4","avatar_url":"https://avatars.githubusercontent.com/u/25657798?v=4","gravatar_id":"","url":"https://api.github.com/users/jwenjian","html_url":"https://github.com/jwenjian","followers_url":"https://api.github.com/users/jwenjian/followers","following_url":"https://api.github.com/users/jwenjian/following{/other_user}","gists_url":"https://api.github.com/users/jwenjian/gists{/gist_id}","starred_url":"https://api.github.com/users/jwenjian/starred{/owner}{/repo}","subscriptions_url":"https://api.github.com/users/jwenjian/subscriptions","organizations_url":"https://api.github.com/users/jwenjian/orgs","repos_url":"https://api.github.com/users/jwenjian/repos","events_url":"https://api.github.com/users/jwenjian/events{/privacy}","received_events_url":"https://api.github.com/users/jwenjian/received_events","type":"User","site_admin":false},"labels":[],"state":"open","locked":false,"assignee":null,"assignees":[],"milestone":null,"comments":0,"created_at":"2021-03-15T06:41:42Z","updated_at":"2021-03-15T06:41:42Z","closed_at":null,"author_association":"OWNER","active_lock_reason":null,"body":"https://www.infoq.com/news/2021/03/end-of-applets/?utm_campaign=infoq_content&utm_source=infoq&utm_medium=feed&utm_term=news","performed_via_github_app":null},{"url":"https://api.github.com/repos/jwenjian/reading-list/issues/102","repository_url":"https://api.github.com/repos/jwenjian/reading-list","labels_url":"https://api.github.com/repos/jwenjian/reading-list/issues/102/labels{/name}","comments_url":"https://api.github.com/repos/jwenjian/reading-list/issues/102/comments","events_url":"https://api.github.com/repos/jwenjian/reading-list/issues/102/events","html_url":"https://github.com/jwenjian/reading-list/issues/102","id":831396174,"node_id":"MDU6SXNzdWU4MzEzOTYxNzQ=","number":102,"title":"中国南部的一家家具装饰公司用白色陶瓷铸造了一个特朗普的雕塑，他双腿盘坐，双手安详地放在膝盖上。他身着僧袍，低着头，闭着眼睛，仿佛在冥想。\n\n艺术家将它起名为“西天懂佛特朗普”。","user":{"login":"jwenjian","id":25657798,"node_id":"MDQ6VXNlcjI1NjU3Nzk4","avatar_url":"https://avatars.githubusercontent.com/u/25657798?v=4","gravatar_id":"","url":"https://api.github.com/users/jwenjian","html_url":"https://github.com/jwenjian","followers_url":"https://api.github.com/users/jwenjian/followers","following_url":"https://api.github.com/users/jwenjian/following{/other_user}","gists_url":"https://api.github.com/users/jwenjian/gists{/gist_id}","starred_url":"https://api.github.com/users/jwenjian/starred{/owner}{/repo}","subscriptions_url":"https://api.github.com/users/jwenjian/subscriptions","organizations_url":"https://api.github.com/users/jwenjian/orgs","repos_url":"https://api.github.com/users/jwenjian/repos","events_url":"https://api.github.com/users/jwenjian/events{/privacy}","received_events_url":"https://api.github.com/users/jwenjian/received_events","type":"User","site_admin":false},"labels":[],"state":"open","locked":false,"assignee":null,"assignees":[],"milestone":null,"comments":0,"created_at":"2021-03-15T04:29:07Z","updated_at":"2021-03-15T04:29:07Z","closed_at":null,"author_association":"OWNER","active_lock_reason":null,"body":"https://cn.nytimes.com/china/20210315/china-trump-buddha/","performed_via_github_app":null},{"url":"https://api.github.com/repos/jwenjian/reading-list/issues/101","repository_url":"https://api.github.com/repos/jwenjian/reading-list","labels_url":"https://api.github.com/repos/jwenjian/reading-list/issues/101/labels{/name}","comments_url":"https://api.github.com/repos/jwenjian/reading-list/issues/101/comments","events_url":"https://api.github.com/repos/jwenjian/reading-list/issues/101/events","html_url":"https://github.com/jwenjian/reading-list/issues/101","id":831386320,"node_id":"MDU6SXNzdWU4MzEzODYzMjA=","number":101,"title":"你爱吃甘蔗吗?你知道甘蔗的根根和尖尖，哪头更甜吗[doge]","user":{"login":"jwenjian","id":25657798,"node_id":"MDQ6VXNlcjI1NjU3Nzk4","avatar_url":"https://avatars.githubusercontent.com/u/25657798?v=4","gravatar_id":"","url":"https://api.github.com/users/jwenjian","html_url":"https://github.com/jwenjian","followers_url":"https://api.github.com/users/jwenjian/followers","following_url":"https://api.github.com/users/jwenjian/following{/other_user}","gists_url":"https://api.github.com/users/jwenjian/gists{/gist_id}","starred_url":"https://api.github.com/users/jwenjian/starred{/owner}{/repo}","subscriptions_url":"https://api.github.com/users/jwenjian/subscriptions","organizations_url":"https://api.github.com/users/jwenjian/orgs","repos_url":"https://api.github.com/users/jwenjian/repos","events_url":"https://api.github.com/users/jwenjian/events{/privacy}","received_events_url":"https://api.github.com/users/jwenjian/received_events","type":"User","site_admin":false},"labels":[],"state":"open","locked":false,"assignee":null,"assignees":[],"milestone":null,"comments":0,"created_at":"2021-03-15T04:03:58Z","updated_at":"2021-03-15T04:03:58Z","closed_at":null,"author_association":"OWNER","active_lock_reason":null,"body":"https://m.weibo.cn/status/4614981855220350?","performed_via_github_app":null},{"url":"https://api.github.com/repos/jwenjian/reading-list/issues/100","repository_url":"https://api.github.com/repos/jwenjian/reading-list","labels_url":"https://api.github.com/repos/jwenjian/reading-list/issues/100/labels{/name}","comments_url":"https://api.github.com/repos/jwenjian/reading-list/issues/100/comments","events_url":"https://api.github.com/repos/jwenjian/reading-list/issues/100/events","html_url":"https://github.com/jwenjian/reading-list/issues/100","id":831317577,"node_id":"MDU6SXNzdWU4MzEzMTc1Nzc=","number":100,"title":"SpaceX 将在2周内部署第3批Starlink 卫星","user":{"login":"jwenjian","id":25657798,"node_id":"MDQ6VXNlcjI1NjU3Nzk4","avatar_url":"https://avatars.githubusercontent.com/u/25657798?v=4","gravatar_id":"","url":"https://api.github.com/users/jwenjian","html_url":"https://github.com/jwenjian","followers_url":"https://api.github.com/users/jwenjian/followers","following_url":"https://api.github.com/users/jwenjian/following{/other_user}","gists_url":"https://api.github.com/users/jwenjian/gists{/gist_id}","starred_url":"https://api.github.com/users/jwenjian/starred{/owner}{/repo}","subscriptions_url":"https://api.github.com/users/jwenjian/subscriptions","organizations_url":"https://api.github.com/users/jwenjian/orgs","repos_url":"https://api.github.com/users/jwenjian/repos","events_url":"https://api.github.com/users/jwenjian/events{/privacy}","received_events_url":"https://api.github.com/users/jwenjian/received_events","type":"User","site_admin":false},"labels":[],"state":"open","locked":false,"assignee":null,"assignees":[],"milestone":null,"comments":0,"created_at":"2021-03-15T01:03:04Z","updated_at":"2021-03-15T01:03:04Z","closed_at":null,"author_association":"OWNER","active_lock_reason":null,"body":"https://techcrunch.com/2021/03/14/spacex-flies-falcon-9-rocket-booster-for-a-record-9th-time-delivers-3rd-batch-of-starlink-satellites-in-two-weeks/","performed_via_github_app":null}],"recent":[{"url":"https://api.github.com/repos/jwenjian/reading-list/issues/99","repository_url":"https://api.github.com/repos/jwenjian/reading-list","labels_url":"https://api.github.com/repos/jwenjian/reading-list/issues/99/labels{/name}","comments_url":"https://api.github.com/repos/jwenjian/reading-list/issues/99/comments","events_url":"https://api.github.com/repos/jwenjian/reading-list/issues/99/events","html_url":"https://github.com/jwenjian/reading-list/issues/99","id":831156059,"node_id":"MDU6SXNzdWU4MzExNTYwNTk=","number":99,"title":"苹果播客将用“关注（follow）”取代“订阅（subscribe）”，因为据调查显示有47%的未使用播客的人认为 订阅(subscribe) 一个播客需要花钱","user":{"login":"jwenjian","id":25657798,"node_id":"MDQ6VXNlcjI1NjU3Nzk4","avatar_url":"https://avatars.githubusercontent.com/u/25657798?v=4","gravatar_id":"","url":"https://api.github.com/users/jwenjian","html_url":"https://github.com/jwenjian","followers_url":"https://api.github.com/users/jwenjian/followers","following_url":"https://api.github.com/users/jwenjian/following{/other_user}","gists_url":"https://api.github.com/users/jwenjian/gists{/gist_id}","starred_url":"https://api.github.com/users/jwenjian/starred{/owner}{/repo}","subscriptions_url":"https://api.github.com/users/jwenjian/subscriptions","organizations_url":"https://api.github.com/users/jwenjian/orgs","repos_url":"https://api.github.com/users/jwenjian/repos","events_url":"https://api.github.com/users/jwenjian/events{/privacy}","received_events_url":"https://api.github.com/users/jwenjian/received_events","type":"User","site_admin":false},"labels":[],"state":"open","locked":false,"assignee":null,"assignees":[],"milestone":null,"comments":0,"created_at":"2021-03-14T13:27:06Z","updated_at":"2021-03-14T13:27:06Z","closed_at":null,"author_association":"OWNER","active_lock_reason":null,"body":"https://www.solidot.org/story?sid=67194","performed_via_github_app":null},{"url":"https://api.github.com/repos/jwenjian/reading-list/issues/98","repository_url":"https://api.github.com/repos/jwenjian/reading-list","labels_url":"https://api.github.com/repos/jwenjian/reading-list/issues/98/labels{/name}","comments_url":"https://api.github.com/repos/jwenjian/reading-list/issues/98/comments","events_url":"https://api.github.com/repos/jwenjian/reading-list/issues/98/events","html_url":"https://github.com/jwenjian/reading-list/issues/98","id":831152678,"node_id":"MDU6SXNzdWU4MzExNTI2Nzg=","number":98,"title":"日本的一个社交软件 (CrabHouse) 被 App Store 拒绝上架更新，拒绝原因是： App 名字令人困惑，有人猜测是 App Store 审核人员把这个 App 当成了 ClubHouse 的翻版","user":{"login":"jwenjian","id":25657798,"node_id":"MDQ6VXNlcjI1NjU3Nzk4","avatar_url":"https://avatars.githubusercontent.com/u/25657798?v=4","gravatar_id":"","url":"https://api.github.com/users/jwenjian","html_url":"https://github.com/jwenjian","followers_url":"https://api.github.com/users/jwenjian/followers","following_url":"https://api.github.com/users/jwenjian/following{/other_user}","gists_url":"https://api.github.com/users/jwenjian/gists{/gist_id}","starred_url":"https://api.github.com/users/jwenjian/starred{/owner}{/repo}","subscriptions_url":"https://api.github.com/users/jwenjian/subscriptions","organizations_url":"https://api.github.com/users/jwenjian/orgs","repos_url":"https://api.github.com/users/jwenjian/repos","events_url":"https://api.github.com/users/jwenjian/events{/privacy}","received_events_url":"https://api.github.com/users/jwenjian/received_events","type":"User","site_admin":false},"labels":[],"state":"open","locked":false,"assignee":null,"assignees":[],"milestone":null,"comments":0,"created_at":"2021-03-14T13:09:36Z","updated_at":"2021-03-14T13:09:36Z","closed_at":null,"author_association":"OWNER","active_lock_reason":null,"body":"https://japantoday.com/category/tech/hit-japanese-app-crabhouse-forced-to-change-name-on-ios","performed_via_github_app":null},{"url":"https://api.github.com/repos/jwenjian/reading-list/issues/97","repository_url":"https://api.github.com/repos/jwenjian/reading-list","labels_url":"https://api.github.com/repos/jwenjian/reading-list/issues/97/labels{/name}","comments_url":"https://api.github.com/repos/jwenjian/reading-list/issues/97/comments","events_url":"https://api.github.com/repos/jwenjian/reading-list/issues/97/events","html_url":"https://github.com/jwenjian/reading-list/issues/97","id":831133010,"node_id":"MDU6SXNzdWU4MzExMzMwMTA=","number":97,"title":"科学家通过分析眼睛的光线反射，开发出一种检测AI 合成的虚假人脸的巧妙方法，有效率达 94%","user":{"login":"jwenjian","id":25657798,"node_id":"MDQ6VXNlcjI1NjU3Nzk4","avatar_url":"https://avatars.githubusercontent.com/u/25657798?v=4","gravatar_id":"","url":"https://api.github.com/users/jwenjian","html_url":"https://github.com/jwenjian","followers_url":"https://api.github.com/users/jwenjian/followers","following_url":"https://api.github.com/users/jwenjian/following{/other_user}","gists_url":"https://api.github.com/users/jwenjian/gists{/gist_id}","starred_url":"https://api.github.com/users/jwenjian/starred{/owner}{/repo}","subscriptions_url":"https://api.github.com/users/jwenjian/subscriptions","organizations_url":"https://api.github.com/users/jwenjian/orgs","repos_url":"https://api.github.com/users/jwenjian/repos","events_url":"https://api.github.com/users/jwenjian/events{/privacy}","received_events_url":"https://api.github.com/users/jwenjian/received_events","type":"User","site_admin":false},"labels":[],"state":"open","locked":false,"assignee":null,"assignees":[],"milestone":null,"comments":0,"created_at":"2021-03-14T11:29:33Z","updated_at":"2021-03-14T11:29:33Z","closed_at":null,"author_association":"OWNER","active_lock_reason":null,"body":"https://thenextweb.com/neural/2021/03/11/ai-detects-deepfakes-analyzing-light-reflections-in-the-cornea-eyes-gans-thispersondoesnotexist/","performed_via_github_app":null},{"url":"https://api.github.com/repos/jwenjian/reading-list/issues/96","repository_url":"https://api.github.com/repos/jwenjian/reading-list","labels_url":"https://api.github.com/repos/jwenjian/reading-list/issues/96/labels{/name}","comments_url":"https://api.github.com/repos/jwenjian/reading-list/issues/96/comments","events_url":"https://api.github.com/repos/jwenjian/reading-list/issues/96/events","html_url":"https://github.com/jwenjian/reading-list/issues/96","id":831132120,"node_id":"MDU6SXNzdWU4MzExMzIxMjA=","number":96,"title":"谷歌面临一项要求50亿美元的集体诉讼，该诉讼声称，即使人们在其Chrome浏览器上使用私人\"隐身\"模式，这家科技巨头也在跟踪和收集数据。","user":{"login":"jwenjian","id":25657798,"node_id":"MDQ6VXNlcjI1NjU3Nzk4","avatar_url":"https://avatars.githubusercontent.com/u/25657798?v=4","gravatar_id":"","url":"https://api.github.com/users/jwenjian","html_url":"https://github.com/jwenjian","followers_url":"https://api.github.com/users/jwenjian/followers","following_url":"https://api.github.com/users/jwenjian/following{/other_user}","gists_url":"https://api.github.com/users/jwenjian/gists{/gist_id}","starred_url":"https://api.github.com/users/jwenjian/starred{/owner}{/repo}","subscriptions_url":"https://api.github.com/users/jwenjian/subscriptions","organizations_url":"https://api.github.com/users/jwenjian/orgs","repos_url":"https://api.github.com/users/jwenjian/repos","events_url":"https://api.github.com/users/jwenjian/events{/privacy}","received_events_url":"https://api.github.com/users/jwenjian/received_events","type":"User","site_admin":false},"labels":[],"state":"open","locked":false,"assignee":null,"assignees":[],"milestone":null,"comments":0,"created_at":"2021-03-14T11:24:22Z","updated_at":"2021-03-14T11:24:22Z","closed_at":null,"author_association":"OWNER","active_lock_reason":null,"body":"https://www.iol.co.za/news/world/google-accused-of-tracking-users-in-incognito-mode-lawsuit-pending-7e0337fd-b4b5-543d-a37d-3af9b5d0b2ea","performed_via_github_app":null},{"url":"https://api.github.com/repos/jwenjian/reading-list/issues/95","repository_url":"https://api.github.com/repos/jwenjian/reading-list","labels_url":"https://api.github.com/repos/jwenjian/reading-list/issues/95/labels{/name}","comments_url":"https://api.github.com/repos/jwenjian/reading-list/issues/95/comments","events_url":"https://api.github.com/repos/jwenjian/reading-list/issues/95/events","html_url":"https://github.com/jwenjian/reading-list/issues/95","id":831116311,"node_id":"MDU6SXNzdWU4MzExMTYzMTE=","number":95,"title":"GIT 最新版本修复了一个安全漏洞，这篇文章分析了这种漏洞的工作机制","user":{"login":"jwenjian","id":25657798,"node_id":"MDQ6VXNlcjI1NjU3Nzk4","avatar_url":"https://avatars.githubusercontent.com/u/25657798?v=4","gravatar_id":"","url":"https://api.github.com/users/jwenjian","html_url":"https://github.com/jwenjian","followers_url":"https://api.github.com/users/jwenjian/followers","following_url":"https://api.github.com/users/jwenjian/following{/other_user}","gists_url":"https://api.github.com/users/jwenjian/gists{/gist_id}","starred_url":"https://api.github.com/users/jwenjian/starred{/owner}{/repo}","subscriptions_url":"https://api.github.com/users/jwenjian/subscriptions","organizations_url":"https://api.github.com/users/jwenjian/orgs","repos_url":"https://api.github.com/users/jwenjian/repos","events_url":"https://api.github.com/users/jwenjian/events{/privacy}","received_events_url":"https://api.github.com/users/jwenjian/received_events","type":"User","site_admin":false},"labels":[],"state":"open","locked":false,"assignee":null,"assignees":[],"milestone":null,"comments":0,"created_at":"2021-03-14T09:54:30Z","updated_at":"2021-03-14T09:54:30Z","closed_at":null,"author_association":"OWNER","active_lock_reason":null,"body":"https://www.infoq.com/news/2021/03/git-clone-vulnerability/?utm_campaign=infoq_content&utm_source=infoq&utm_medium=feed&utm_term=news","performed_via_github_app":null},{"url":"https://api.github.com/repos/jwenjian/reading-list/issues/94","repository_url":"https://api.github.com/repos/jwenjian/reading-list","labels_url":"https://api.github.com/repos/jwenjian/reading-list/issues/94/labels{/name}","comments_url":"https://api.github.com/repos/jwenjian/reading-list/issues/94/comments","events_url":"https://api.github.com/repos/jwenjian/reading-list/issues/94/events","html_url":"https://github.com/jwenjian/reading-list/issues/94","id":831064308,"node_id":"MDU6SXNzdWU4MzEwNjQzMDg=","number":94,"title":"俄罗斯南乌拉尔国立大学的博士 Ildar Rakhmatulin 就创建了一个树莓派机器，利用计算机视觉和机器学习技术自动检测蚊子，并使用激光烧死它们。","user":{"login":"jwenjian","id":25657798,"node_id":"MDQ6VXNlcjI1NjU3Nzk4","avatar_url":"https://avatars.githubusercontent.com/u/25657798?v=4","gravatar_id":"","url":"https://api.github.com/users/jwenjian","html_url":"https://github.com/jwenjian","followers_url":"https://api.github.com/users/jwenjian/followers","following_url":"https://api.github.com/users/jwenjian/following{/other_user}","gists_url":"https://api.github.com/users/jwenjian/gists{/gist_id}","starred_url":"https://api.github.com/users/jwenjian/starred{/owner}{/repo}","subscriptions_url":"https://api.github.com/users/jwenjian/subscriptions","organizations_url":"https://api.github.com/users/jwenjian/orgs","repos_url":"https://api.github.com/users/jwenjian/repos","events_url":"https://api.github.com/users/jwenjian/events{/privacy}","received_events_url":"https://api.github.com/users/jwenjian/received_events","type":"User","site_admin":false},"labels":[],"state":"open","locked":false,"assignee":null,"assignees":[],"milestone":null,"comments":0,"created_at":"2021-03-14T04:47:13Z","updated_at":"2021-03-14T04:47:13Z","closed_at":null,"author_association":"OWNER","active_lock_reason":null,"body":"https://www.jiqizhixin.com/articles/2021-03-14-2","performed_via_github_app":null},{"url":"https://api.github.com/repos/jwenjian/reading-list/issues/93","repository_url":"https://api.github.com/repos/jwenjian/reading-list","labels_url":"https://api.github.com/repos/jwenjian/reading-list/issues/93/labels{/name}","comments_url":"https://api.github.com/repos/jwenjian/reading-list/issues/93/comments","events_url":"https://api.github.com/repos/jwenjian/reading-list/issues/93/events","html_url":"https://github.com/jwenjian/reading-list/issues/93","id":831054483,"node_id":"MDU6SXNzdWU4MzEwNTQ0ODM=","number":93,"title":"为什么气候模型软件要用1950s发明的编程语言 Fortran 语言来编写？","user":{"login":"jwenjian","id":25657798,"node_id":"MDQ6VXNlcjI1NjU3Nzk4","avatar_url":"https://avatars.githubusercontent.com/u/25657798?v=4","gravatar_id":"","url":"https://api.github.com/users/jwenjian","html_url":"https://github.com/jwenjian","followers_url":"https://api.github.com/users/jwenjian/followers","following_url":"https://api.github.com/users/jwenjian/following{/other_user}","gists_url":"https://api.github.com/users/jwenjian/gists{/gist_id}","starred_url":"https://api.github.com/users/jwenjian/starred{/owner}{/repo}","subscriptions_url":"https://api.github.com/users/jwenjian/subscriptions","organizations_url":"https://api.github.com/users/jwenjian/orgs","repos_url":"https://api.github.com/users/jwenjian/repos","events_url":"https://api.github.com/users/jwenjian/events{/privacy}","received_events_url":"https://api.github.com/users/jwenjian/received_events","type":"User","site_admin":false},"labels":[],"state":"open","locked":false,"assignee":null,"assignees":[],"milestone":null,"comments":0,"created_at":"2021-03-14T03:24:55Z","updated_at":"2021-03-14T03:24:55Z","closed_at":null,"author_association":"OWNER","active_lock_reason":null,"body":"https://partee.io/2021/02/21/climate-model-response/\r\n","performed_via_github_app":null},{"url":"https://api.github.com/repos/jwenjian/reading-list/issues/92","repository_url":"https://api.github.com/repos/jwenjian/reading-list","labels_url":"https://api.github.com/repos/jwenjian/reading-list/issues/92/labels{/name}","comments_url":"https://api.github.com/repos/jwenjian/reading-list/issues/92/comments","events_url":"https://api.github.com/repos/jwenjian/reading-list/issues/92/events","html_url":"https://github.com/jwenjian/reading-list/issues/92","id":831051611,"node_id":"MDU6SXNzdWU4MzEwNTE2MTE=","number":92,"title":"科学家揭开世界上最古老的“计算机”(一台拥有2000年历史的设备)之谜","user":{"login":"jwenjian","id":25657798,"node_id":"MDQ6VXNlcjI1NjU3Nzk4","avatar_url":"https://avatars.githubusercontent.com/u/25657798?v=4","gravatar_id":"","url":"https://api.github.com/users/jwenjian","html_url":"https://github.com/jwenjian","followers_url":"https://api.github.com/users/jwenjian/followers","following_url":"https://api.github.com/users/jwenjian/following{/other_user}","gists_url":"https://api.github.com/users/jwenjian/gists{/gist_id}","starred_url":"https://api.github.com/users/jwenjian/starred{/owner}{/repo}","subscriptions_url":"https://api.github.com/users/jwenjian/subscriptions","organizations_url":"https://api.github.com/users/jwenjian/orgs","repos_url":"https://api.github.com/users/jwenjian/repos","events_url":"https://api.github.com/users/jwenjian/events{/privacy}","received_events_url":"https://api.github.com/users/jwenjian/received_events","type":"User","site_admin":false},"labels":[],"state":"open","locked":false,"assignee":null,"assignees":[],"milestone":null,"comments":0,"created_at":"2021-03-14T03:01:56Z","updated_at":"2021-03-14T03:01:56Z","closed_at":null,"author_association":"OWNER","active_lock_reason":null,"body":"https://www.bbc.com/news/science-environment-56377567","performed_via_github_app":null},{"url":"https://api.github.com/repos/jwenjian/reading-list/issues/91","repository_url":"https://api.github.com/repos/jwenjian/reading-list","labels_url":"https://api.github.com/repos/jwenjian/reading-list/issues/91/labels{/name}","comments_url":"https://api.github.com/repos/jwenjian/reading-list/issues/91/comments","events_url":"https://api.github.com/repos/jwenjian/reading-list/issues/91/events","html_url":"https://github.com/jwenjian/reading-list/issues/91","id":831046979,"node_id":"MDU6SXNzdWU4MzEwNDY5Nzk=","number":91,"title":"IIHS在其研究中发现，驾驶员在使用ACC（自适应巡航系统）时更有可能(24%)提速。","user":{"login":"jwenjian","id":25657798,"node_id":"MDQ6VXNlcjI1NjU3Nzk4","avatar_url":"https://avatars.githubusercontent.com/u/25657798?v=4","gravatar_id":"","url":"https://api.github.com/users/jwenjian","html_url":"https://github.com/jwenjian","followers_url":"https://api.github.com/users/jwenjian/followers","following_url":"https://api.github.com/users/jwenjian/following{/other_user}","gists_url":"https://api.github.com/users/jwenjian/gists{/gist_id}","starred_url":"https://api.github.com/users/jwenjian/starred{/owner}{/repo}","subscriptions_url":"https://api.github.com/users/jwenjian/subscriptions","organizations_url":"https://api.github.com/users/jwenjian/orgs","repos_url":"https://api.github.com/users/jwenjian/repos","events_url":"https://api.github.com/users/jwenjian/events{/privacy}","received_events_url":"https://api.github.com/users/jwenjian/received_events","type":"User","site_admin":false},"labels":[],"state":"open","locked":false,"assignee":null,"assignees":[],"milestone":null,"comments":0,"created_at":"2021-03-14T02:21:39Z","updated_at":"2021-03-14T02:21:39Z","closed_at":null,"author_association":"OWNER","active_lock_reason":null,"body":"https://arstechnica.com/cars/2021/03/adaptive-cruise-control-users-more-likely-to-speed-study-finds/\r\n","performed_via_github_app":null},{"url":"https://api.github.com/repos/jwenjian/reading-list/issues/90","repository_url":"https://api.github.com/repos/jwenjian/reading-list","labels_url":"https://api.github.com/repos/jwenjian/reading-list/issues/90/labels{/name}","comments_url":"https://api.github.com/repos/jwenjian/reading-list/issues/90/comments","events_url":"https://api.github.com/repos/jwenjian/reading-list/issues/90/events","html_url":"https://github.com/jwenjian/reading-list/issues/90","id":831046234,"node_id":"MDU6SXNzdWU4MzEwNDYyMzQ=","number":90,"title":"随着浏览器的使用率下降到1％以下，最著名和最受欢迎的博客平台WordPress正在考虑放弃对Internet Explorer 11的支持。","user":{"login":"jwenjian","id":25657798,"node_id":"MDQ6VXNlcjI1NjU3Nzk4","avatar_url":"https://avatars.githubusercontent.com/u/25657798?v=4","gravatar_id":"","url":"https://api.github.com/users/jwenjian","html_url":"https://github.com/jwenjian","followers_url":"https://api.github.com/users/jwenjian/followers","following_url":"https://api.github.com/users/jwenjian/following{/other_user}","gists_url":"https://api.github.com/users/jwenjian/gists{/gist_id}","starred_url":"https://api.github.com/users/jwenjian/starred{/owner}{/repo}","subscriptions_url":"https://api.github.com/users/jwenjian/subscriptions","organizations_url":"https://api.github.com/users/jwenjian/orgs","repos_url":"https://api.github.com/users/jwenjian/repos","events_url":"https://api.github.com/users/jwenjian/events{/privacy}","received_events_url":"https://api.github.com/users/jwenjian/received_events","type":"User","site_admin":false},"labels":[],"state":"open","locked":false,"assignee":null,"assignees":[],"milestone":null,"comments":0,"created_at":"2021-03-14T02:15:01Z","updated_at":"2021-03-14T02:15:01Z","closed_at":null,"author_association":"OWNER","active_lock_reason":null,"body":"https://www.bleepingcomputer.com/news/software/wordpress-plans-to-drop-support-for-internet-explorer-11/\r\n","performed_via_github_app":null}]}